odoo9_addon_contract_invoice_merge_by_partner-9.0.2.0.0-py2.7-nspkg.pth
odoo9_addon_contract_invoice_merge_by_partner-9.0.2.0.0.dist-info/DESCRIPTION.rst
odoo9_addon_contract_invoice_merge_by_partner-9.0.2.0.0.dist-info/METADATA
odoo9_addon_contract_invoice_merge_by_partner-9.0.2.0.0.dist-info/RECORD
odoo9_addon_contract_invoice_merge_by_partner-9.0.2.0.0.dist-info/WHEEL
odoo9_addon_contract_invoice_merge_by_partner-9.0.2.0.0.dist-info/metadata.json
odoo9_addon_contract_invoice_merge_by_partner-9.0.2.0.0.dist-info/namespace_packages.txt
odoo9_addon_contract_invoice_merge_by_partner-9.0.2.0.0.dist-info/top_level.txt
odoo_addons/contract_invoice_merge_by_partner/README.rst
odoo_addons/contract_invoice_merge_by_partner/__init__.py
odoo_addons/contract_invoice_merge_by_partner/__openerp__.py
odoo_addons/contract_invoice_merge_by_partner/i18n/am.po
odoo_addons/contract_invoice_merge_by_partner/i18n/ar.po
odoo_addons/contract_invoice_merge_by_partner/i18n/bg.po
odoo_addons/contract_invoice_merge_by_partner/i18n/bs.po
odoo_addons/contract_invoice_merge_by_partner/i18n/ca.po
odoo_addons/contract_invoice_merge_by_partner/i18n/cs.po
odoo_addons/contract_invoice_merge_by_partner/i18n/da.po
odoo_addons/contract_invoice_merge_by_partner/i18n/de.po
odoo_addons/contract_invoice_merge_by_partner/i18n/el_GR.po
odoo_addons/contract_invoice_merge_by_partner/i18n/en_GB.po
odoo_addons/contract_invoice_merge_by_partner/i18n/es.po
odoo_addons/contract_invoice_merge_by_partner/i18n/es_CR.po
odoo_addons/contract_invoice_merge_by_partner/i18n/es_EC.po
odoo_addons/contract_invoice_merge_by_partner/i18n/es_MX.po
odoo_addons/contract_invoice_merge_by_partner/i18n/es_VE.po
odoo_addons/contract_invoice_merge_by_partner/i18n/et.po
odoo_addons/contract_invoice_merge_by_partner/i18n/eu.po
odoo_addons/contract_invoice_merge_by_partner/i18n/fi.po
odoo_addons/contract_invoice_merge_by_partner/i18n/fr.po
odoo_addons/contract_invoice_merge_by_partner/i18n/fr_CA.po
odoo_addons/contract_invoice_merge_by_partner/i18n/fr_CH.po
odoo_addons/contract_invoice_merge_by_partner/i18n/gl.po
odoo_addons/contract_invoice_merge_by_partner/i18n/hr.po
odoo_addons/contract_invoice_merge_by_partner/i18n/hr_HR.po
odoo_addons/contract_invoice_merge_by_partner/i18n/hu.po
odoo_addons/contract_invoice_merge_by_partner/i18n/it.po
odoo_addons/contract_invoice_merge_by_partner/i18n/ja.po
odoo_addons/contract_invoice_merge_by_partner/i18n/lt.po
odoo_addons/contract_invoice_merge_by_partner/i18n/lv.po
